MANIFEST.in
README.rst
requirements.txt
setup.py
gromozeka/__init__.py
gromozeka.egg-info/PKG-INFO
gromozeka.egg-info/SOURCES.txt
gromozeka.egg-info/dependency_links.txt
gromozeka.egg-info/not-zip-safe
gromozeka.egg-info/requires.txt
gromozeka.egg-info/top_level.txt
gromozeka/app/__init__.py
gromozeka/app/app.py
gromozeka/backends/__init__.py
gromozeka/backends/base.py
gromozeka/backends/redis.py
gromozeka/brokers/__init__.py
gromozeka/brokers/base.py
gromozeka/brokers/rabbit.py
gromozeka/concurrency/__init__.py
gromozeka/concurrency/commands.py
gromozeka/concurrency/pool.py
gromozeka/concurrency/scheduler.py
gromozeka/concurrency/worker.py
gromozeka/config/__init__.py
gromozeka/exceptions/__init__.py
gromozeka/primitives/__init__.py
gromozeka/primitives/base.py
gromozeka/primitives/dag.py
gromozeka/primitives/task_pb2.py
requirements/base.txt
requirements/develop.txt
requirements/docs.txt
requirements/rabbit.txt
requirements/redis.txt
requirements/visual.txt