Metadata-Version: 2.1
Name: gromozeka
Version: 0.1.2
Summary: Distributed task queue.
Home-page: https://github.com/moelius/gromozeka
Author: Klimov Konstantin
Author-email: moelius1983@gmail.com
License: MIT
Keywords: task job queue distributed messaging pika rabbit rabbitmq pool worker
Platform: UNKNOWN
Provides-Extra: docs
Provides-Extra: visual
